[
  {
    "text": "  Чат-Бот с переводчиком для общения с иностранцем.\nЧтобы ваши сообщения дублировалиcь на другом языке наберите \"/L **\" , где вместо ** подставить код языка: ru, en, de, fr, zh, ja, ar, ... .\n   Коды языков здесь:\n\"https://yandex.ru/dev/translate/doc/dg/concepts/api-overview-docpage/#api-overview__languages\" .\n  После все сообщения будут с переводом на выбранном языке.\nЧтобы убрать перевод введите просто \"/L\" без кода\n",
    "timestamp": 1592564494.422693,
    "username": ""
  },
  {
    "text": "Привет! ",
    "timestamp": 1592564623.06144,
    "username": "marat"
  }
]